zebullconnect/zebullapi.py
zebull-2.2.dist-info/LICENSE.txt
zebull-2.2.dist-info/METADATA
zebull-2.2.dist-info/WHEEL
zebull-2.2.dist-info/top_level.txt
zebull-2.2.dist-info/RECORD
