Metadata-Version: 2.1
Name: zebull
Version: 2.2
Summary: Python SDK for API users
Home-page: https://zebull.in
Author: Stoneage Solutions
Author-email: pradeep@stoneagesolutions.com
License: MIT
Platform: UNKNOWN
Classifier: Programming Language :: Python :: 3.9
Classifier: License :: OSI Approved :: MIT License
Classifier: Operating System :: OS Independent
Classifier: Natural Language :: English
Classifier: Intended Audience :: Developers
Requires-Python: >=3.0
